{
    "id": "12247",
    "name": "陳伙悌、張陳伙俤、陳伙俤",
    "gender": "女",
    "birth_h": "1923",
    "province": "福建",
    "city": "林森縣",
    "edu": "暫無資料",
    "d1_num": "暫無資料",
    "occupation": "無",
    "age": "38",
    "d1_per1": "暫無資料",
    "d1_crime1": "暫無資料",
    "d1_crime1cat": "暫無資料",
    "d1_law1": "暫無資料",
    "d1_prosec": "無",
    "d1_pa1": "暫無資料",
    "d1_clk1": "暫無資料",
    "d2_doc": "其他",
    "d2_num1": "(48)警審聲字第31號",
    "d2_authority": "台灣警備總司令部",
    "d2_pa1": "桑振業",
    "d2_main1": "交付感化三年",
    "d2_edu": "有",
    "d2_eduy": "3",
    "d2_crime1": "於民國三十九年七月間，被福州匪偽任為鴨姆洲居民小組長，及婦女會會員，嗣於民國四十年三月，受匪福建海防局情報股長齊匪文斌指示，潛來馬祖白肯說服其夫張劍飛(即張順)為匪工作",
    "d2_crime1cat": "情節輕微而有感化必要者，交付感化",
    "d2_law1": "戡亂時期檢肅匪諜條例",
    "d2_law1a": "8",
    "d2_law1s": "1",
    "d2_law1i": "2",
    "d2_j1": "陳文緯",
    "d2_jpos1": "審判官",
    "d2_clk1": "劉齊",
    "d2_y": "49",
    "d2_m": "3",
    "d2_d": "28",
    "d2_rejud": "無",
    "f_authority": "台灣警備總司令部",
    "f_jyear": "49",
    "f_num": "(48)警審聲字第0031號",
    "f_pa1": "桑振業",
    "f_attycat": "暫無資料",
    "f_main1": "交付感化三年",
    "f_group": "鴨姆洲居民小組、婦女會",
    "f_per1": "暫無資料",
    "f_law1": "戡亂時期檢肅匪諜條例",
    "f_law1a": "8",
    "f_law1s": "1",
    "f_law1i": "2",
    "f_penaltytxt": "感化教育3年",
    "f_forf": "無",
    "f_j1": "陳文緯",
    "f_clk1": "劉齊",
    "f_y": "49",
    "f_m": "3",
    "f_d": "28",
    "f_txt": "【裁判字號】48，警審聲，0031\n【裁判日期】490328\n【裁判機關】台灣警備司令部\n【受裁判者】陳伙悌\n【類　　別】判決書\n【裁判全文】\n\n台灣警備總司令部判決　　　　　　　　　　　　　　　　　　　　　　（４８）警審聲字３１號\n公訴人　本部軍事檢察官\n被　告　陳伙悌　　女　年卅八歲 　福建林森人 住基隆市  業無在保\n　　　　　　\n右聲請人因被告叛亂嫌疑案件，聲請交付感化，本部裁定如左：\n  　主文\n陳伙悌　交付感化三年。\n　　理由\n本件軍事檢察官聲請意旨，略以被告陳伙悌　由於民國三十九年七月間，被福州匪偽任為鴨姆洲居民小組長，及婦女會會員，嗣於民國四十年三月，受匪福建海防局情報股長齊匪文斌指示，潛來馬祖白肯說服其夫張劍飛（即張順）為匪工作，案經司法行政部調查局查獲移送本部偵辦。訊據被告陳伙悌　對於上開事實，均坦承無隱，以該被告曾任匪之居民小組長及婦女會會員之事，雖已　　　\n　　　　　匪份子登記，但對應允齊匪說服其夫為匪工作一節，并未向晤說出，縱　事後調查未曾實施，究其行為仍難謂非違法，況登記時間　在調查局　另案查問張劍飛供出實情之後，顯見其尚未　於澈底悔悟之程度，核其　節，尚屬輕微，認有交付感化之必要，聲請裁定前來，經覆核無異，應予照准，爰依戡亂時期檢蕭匪諜條例第八條第　項第二款，裁定如主文。\n中　華　民　國　四　十　五　年　　月　　日\n台灣警備總司令部簡易審判庭\n審判官　陳文緯\n右裁定正本證明與原本無異。\n如不服本裁定應於送達後五日內以書面敘述抗告之理由提出於本部提起抗告。\n書記官　劉　齊\n中　華　民　國　四　十　九　年　三　月　廿　八　日"
}