{
    "id": "13028",
    "name": "蔡景霖",
    "gender": "男",
    "birth_h": "1945",
    "province": "臺灣省",
    "city": "臺中市",
    "edu": "暫無資料",
    "d1_authority": "情報局",
    "d1_num": "(56)檢聲字第003號",
    "occupation": "國防部情報局情報幹部訓練班第十五期學生",
    "age": "22",
    "d1_crime1": "民國五十四年九月間就讀台中光華工業職業學校時結識其妹蔡彩薇同房居住之台中家事職業學校學生鄭淑華，是年中秋節後某日被告囑其妹詢鄭女是否有意參加台灣獨立組織，事為鄭女所拒，未幾蔡女因口角掌摑鄭女，並向該校教官稱鄭女偷其金錢，因而鄭女將前情向該校教官報告。旋經台灣省警務處令飭南投縣，彰化縣，台中市警察局組織專案小組，因查無事證，停止偵查，嗣被告於民國五十五年九月十日考入本局情幹班受訓，該班於新生調查資料中審知被告前曾涉嫌「台獨」案件，乃指定專人考核，發覺其在班內仍有挑撥同學感情，試探考核人員對「台獨」反應等活動情形",
    "d1_crime1cat": "情節輕微而有感化必要者，交付感化",
    "d1_law1": "戡亂時期檢肅匪諜條例",
    "d1_law1a": "8",
    "d1_law1s": "1",
    "d1_law1i": "2",
    "d1_prosec": "無",
    "d1_edu": "有",
    "d1_sentenc": "有",
    "d1_pa1": "孫域",
    "d1_clk1": "楊光亞",
    "d1_y": "57",
    "d1_m": "1",
    "d1_d": "3",
    "d2_doc": "其他",
    "d2_num1": "(57)甸平裁字第017號",
    "d2_authority": "國防部情報局",
    "d2_main1": "交付感化三年",
    "d2_edu": "有",
    "d2_eduy": "3",
    "d2_crime1": "民國五十四年十月間，在台中光華工業職業學校就讀時，曾先後徵求其同學陳銘男、朱正傑、及其妹同學台中家事職業學校學生鄭淑華，參加「台灣獨立」運動，事為鄭女向該校軍訓教官檢舉，轉經台灣省警務處令飭南投縣、彰化縣、台中市等警察局調查。嗣被告於民國五十五年九月考入本局情報幹部訓練班十五期受訓，該班發覺被告又先後向該班本省籍隊職人員何健藏、簡正男試探對台灣獨立運動興趣等不法情事",
    "d2_crime1cat": "情節輕微而有感化必要者，交付感化",
    "d2_law1": "戡亂時期檢肅匪諜條例",
    "d2_law1a": "8",
    "d2_law1s": "1",
    "d2_law1i": "2",
    "d2_law2": "戡亂時期匪諜交付感化辦法",
    "d2_law2a": "2",
    "d2_j1": "劉樹錚",
    "d2_jpos1": "審判官",
    "d2_clk1": "黃明友",
    "d2_y": "57",
    "d2_m": "4",
    "d2_d": "30",
    "d2_rejud": "無",
    "f_authority": "情報局",
    "f_jyear": "57",
    "f_num": "(57)甸平裁字第17號",
    "f_attycat": "暫無資料",
    "f_main1": "交付感化三年",
    "f_law1": "戡亂時期檢肅匪諜條例",
    "f_law1a": "8",
    "f_law1s": "1",
    "f_law1i": "2",
    "f_law2": "戡亂時期匪諜交付感化辦法",
    "f_law2a": "2",
    "f_penaltytxt": "感化教育3年",
    "f_edu": "有",
    "f_eduy": "3",
    "f_forf": "無",
    "f_j1": "劉樹錚",
    "f_clk1": "黃明友",
    "f_y": "57",
    "f_m": "4",
    "f_d": "30",
    "f_txt": "暫無資料"
}