{
    "id": "15389",
    "name": "林如松",
    "gender": "男",
    "birth_h": "1927",
    "province": "臺灣省",
    "city": "臺中市",
    "edu": "暫無資料",
    "d1_num": "暫無資料",
    "occupation": "台中師範三年級學生",
    "age": "22",
    "d1_per1": "暫無資料",
    "d1_crime1": "暫無資料",
    "d1_crime1cat": "暫無資料",
    "d1_law1": "暫無資料",
    "d1_prosec": "無",
    "d1_pa1": "暫無資料",
    "d1_clk1": "暫無資料",
    "d2_doc": "公文（代電、稿、簽呈等）",
    "d2_num1": "(39)安潔字第2154號",
    "d2_authority": "台灣省保安司令部",
    "d2_main1": "共同意圖以非法方法顛覆政府而著手實行",
    "d2_per1": "施部生",
    "d2_per2": "呂煥章",
    "d2_per3": "張建三",
    "d2_per4": "李金木",
    "d2_per5": "莊朝鐘",
    "d2_per6": "彭沐興",
    "d2_per7": "黃士性",
    "d2_per8": "劉嘉憲",
    "d2_per9": "許溪河",
    "d2_per10": "嚴勝河",
    "d2_per11": "尤昭榮",
    "d2_per12": "劉水生",
    "d2_per13": "傅鍾韓",
    "d2_per14": "賴水池",
    "d2_per15": "隋宗清",
    "d2_per16": "溫傳旺",
    "d2_per17": "黃士樓",
    "d2_life": "有",
    "d2_dpriv": "有",
    "d2_dprivy": "終身",
    "d2_law1": "懲治叛亂條例",
    "d2_law1a": "2",
    "d2_law1s": "1",
    "d2_law2": "刑法",
    "d2_law2a": "100",
    "d2_law2s": "1",
    "d2_law3": "刑法",
    "d2_law3a": "28",
    "d2_law4": "刑法",
    "d2_law4a": "59",
    "d2_law5": "懲治叛亂條例",
    "d2_law5a": "4",
    "d2_law5s": "1",
    "d2_law5i": "4",
    "d2_law6": "刑法",
    "d2_law6a": "29",
    "d2_law7": "刑法",
    "d2_law7a": "55",
    "d2_j1": "殷敬文",
    "d2_jpos1": "審判官",
    "d2_clk1": "黃柱中",
    "d2_y": "39",
    "d2_m": "9",
    "d2_d": "14",
    "d3_doc": "公文（代電、稿、簽呈等）",
    "d3_num1": "(39)法簽字第374號",
    "d3_authority": "國防部",
    "d3_death": "有",
    "d3_dpriv": "有",
    "d3_dprivy": "終身",
    "d3_crime1": "施部生、呂煥章在三十六年間先後加入共匪台灣工作委員會台中地區縣市工委會之部組織……被告莊朝鐘許溪河張建三嚴勝河尤昭榮李金木賴水池黃士性傅鍾韓劉嘉憲林如松彭沐興劉水生等均相繼參加",
    "d3_crime1cat": "意圖破壞國體、竊據國土或以非法之方法變更國憲、顛覆政府，而著手實行者",
    "d3_j1": "郭寄嶠",
    "d3_jpos1": "副參謀總長(執行官)",
    "d3_y": "39",
    "d3_m": "10",
    "d3_d": "8",
    "d3_revrec": "不同意，有提出刑度",
    "d4_doc": "公文（代電、稿、簽呈等）",
    "d4_num2": "暫無資料",
    "d4_authority": "總統（府）",
    "d4_crime1": "未提及罪行",
    "d4_crime1cat": "未提及罪行",
    "d4_j1": "劉士毅",
    "d4_jpos1": "總統府參軍長",
    "d4_y": "39",
    "d4_m": "10",
    "d4_d": "12",
    "d4_revrec": "同意",
    "d5_doc": "公文（代電、稿、簽呈等）",
    "d5_num2": "暫無資料",
    "d5_authority": "總統（府）",
    "d5_crime1": "未提及罪行",
    "d5_crime1cat": "未提及罪行",
    "d5_j1": "蔣中正",
    "d5_jpos1": "總統",
    "d5_y": "39",
    "d5_m": "10",
    "d5_d": "27",
    "d5_presw": "如擬",
    "d5_revrec": "同意",
    "d6_doc": "公文（代電、稿、簽呈等）",
    "d6_num1": "(39)聯芬字第390299號",
    "d6_authority": "總統（府）",
    "d6_crime1": "未提及罪行",
    "d6_crime1cat": "未提及罪行",
    "d6_j1": "蔡大冶",
    "d6_jpos1": "總統府駐國防部連絡室高參",
    "d6_y": "39",
    "d6_m": "10",
    "d6_d": "30",
    "d6_revrec": "同意",
    "d7_doc": "公文（代電、稿、簽呈等）",
    "d7_num1": "(39)勳助字第954號",
    "d7_authority": "國防部",
    "d7_crime1": "未提及罪行",
    "d7_crime1cat": "未提及罪行",
    "d7_j1": "周至柔",
    "d7_jpos1": "參謀總長",
    "d7_y": "39",
    "d7_m": "11",
    "d7_d": "4",
    "d7_revrec": "同意",
    "d8_doc": "判決書",
    "d8_num1": "(39)安潔字第2154號",
    "d8_authority": "台灣省保安司令部",
    "d8_main1": "共同意圖以非法方法顛覆政府而著手實行",
    "d8_per1": "施部生",
    "d8_per2": "呂煥章",
    "d8_per3": "張建三",
    "d8_per4": "李金木",
    "d8_per5": "莊朝鐘",
    "d8_per6": "彭沐興",
    "d8_per7": "黃士性",
    "d8_per8": "劉嘉憲",
    "d8_per9": "許溪河",
    "d8_per10": "嚴勝河",
    "d8_per11": "尤昭榮",
    "d8_per12": "劉水生",
    "d8_per13": "傅鍾韓",
    "d8_per14": "賴水池",
    "d8_per15": "隋宗清",
    "d8_per16": "溫傳旺",
    "d8_per17": "黃士樓",
    "d8_death": "有",
    "d8_dpriv": "有",
    "d8_dprivy": "終身",
    "d8_law1": "懲治叛亂條例",
    "d8_law1a": "2",
    "d8_law1s": "1",
    "d8_law2": "刑法",
    "d8_law2a": "100",
    "d8_law2s": "1",
    "d8_law3": "刑法",
    "d8_law3a": "28",
    "d8_law4": "懲治叛亂條例",
    "d8_law4a": "4",
    "d8_law4s": "1",
    "d8_law4i": "4",
    "d8_law5": "刑法",
    "d8_law5a": "29",
    "d8_law6": "刑法",
    "d8_law6a": "55",
    "d8_j1": "殷敬文",
    "d8_jpos1": "審判官",
    "d8_clk1": "黃柱中",
    "d8_y": "39",
    "d8_m": "11",
    "d8_d": "4",
    "d8_rejud": "無",
    "d8_revrec": "不適用",
    "f_authority": "台灣省保安司令部",
    "f_jyear": "39",
    "f_num": "(39)安潔字第2154號",
    "f_main1": "共同意圖以非法方法顛覆政府而著手實行",
    "f_group": "歷年辦理匪案彙編：匪台灣省工委會台中武裝工委會",
    "f_per1": "施部生",
    "f_per2": "呂煥章",
    "f_per3": "張建三",
    "f_per4": "李金木",
    "f_per5": "莊朝鐘",
    "f_per6": "彭沐興",
    "f_per7": "黃士性",
    "f_per8": "劉嘉憲",
    "f_per9": "許溪河",
    "f_per10": "嚴勝河",
    "f_per11": "尤昭榮",
    "f_per12": "劉水生",
    "f_per13": "傅鍾韓",
    "f_per14": "賴水池",
    "f_per15": "隋宗清",
    "f_per16": "溫傳旺",
    "f_per17": "黃士樓",
    "f_law1": "懲治叛亂條例",
    "f_law1a": "2",
    "f_law1s": "1",
    "f_law2": "刑法",
    "f_law2a": "100",
    "f_law2s": "1",
    "f_law3": "刑法",
    "f_law3a": "28",
    "f_law4": "懲治叛亂條例",
    "f_law4a": "4",
    "f_law4s": "1",
    "f_law4i": "4",
    "f_law5": "刑法",
    "f_law5a": "29",
    "f_law6": "刑法",
    "f_law6a": "55",
    "f_penaltytxt": "死刑",
    "f_death": "有",
    "f_forf": "有",
    "f_j1": "殷敬文",
    "f_clk1": "黃柱中",
    "f_y": "39",
    "f_m": "11",
    "f_d": "4",
    "f_txt": "【裁判字號】39，安潔，2154\n【裁判日期】390907\n【裁判機關】台灣省保安司令部\n【受裁判者】施部生，呂煥章，張建三，李金木，莊朝鐘，林如松，彭沐興，黃士性，劉嘉憲，嚴勝河，許溪河，尤昭荣，劉水生，傅鍾韓，賴水池，隋宗清，温傳旺，黃士樓\n【類　　別】判决書\n【裁判全文】\n\n台灣省保安司令部判决　　　　　　　　　　　　　　　　　　　　　　（39）安潔字第2154號\n　　判决正本\n　　被　告　施部生　男　年二十七歲　夲省台中縣人　無業\n呂煥章　男　年廾七歲　本省台中市人　無業\n張建三　男　年廾歲　本省台中市人　無業\n李金木　男　年廾三歲　本省台中市人　織蓆工\n莊朝鐘　男　年二十三歲　本省台中市人　台中糖厰工務課繪圖員\n林如松　男　年廾三歲　本省台中市人　台中師範三年級學生\n彭沐興　男　年廾一歲　本省新竹縣人　無業\n黃士性　男　年二十四歲　本省台中縣人　台中山林管理所駐新社鄉森林幹事\n劉嘉憲　男　年二十歲　本省台中縣人　新社鄉新社村國民兵隊附\n嚴勝河　男　年二十三歲　本省新竹縣人　無業\n許溪河　男　年二十二歲　本省台中縣人　無業\n尤昭荣　男　年十九歲　本省台中市人　製餅業\n劉水生　男　年二十歲　本省台中縣人　台中商業职業學校高三下學生\n傅鍾韓　男　年二十三歲　福建仙游縣人　大南國民學校宿舍　業教員\n賴水池　男　年二十二歲　本省台中市人　業雜貨商\n隋宗清　男　年二十九歲　山東棲霞縣人　住所無定　前任台中商業职業學校教員\n温傳旺　男　年四十五歲　本省台中縣人　業代工\n黃士樓　男　年二十歲　本省台中縣人　業辳\n右被告等因犯叛乱等罪一案経本部審判如左\n　　　主　文\n施部生呂煥章張建三李金木莊朝鐘共同以暴動意圖顛覆政府而着手寔行各處死刑各褫奪公權終身林如松彭沐興黃士性劉嘉憲共同意圖以非法方法顛覆政府而着手寔行各處死刑各褫奪公權終身\n嚴勝河参加叛乱之組织處無期徒刑褫奪公權終身\n許溪河尤昭榮劉水生傅鍾韓賴水池参加叛乱之組织各處有期徒刑十三年各褫奪公權十年\n隋宗清参加叛乱之集會處有期徒刑十年褫奪公權五年\n温傳旺黃士楼明知為匪諜而不檢舉各處有期徒刑二年\n施部生呂煥章張建三李金木莊朝鍾林如松彭沐興黃士性劉嘉憲全部財産除酌留家属必需生活費外均沒收\n獲案槍弹（詳卷內「白毛山竹子坑两地鹵獲潛匪武器清冊」列載數量）均沒收\n　　　事　實\n被告施部生呂煥章扵三十六年五月及九月間先後由在逃之李舜兩吸收加入奸匪台灣工作委員會台中地區縣市工委會支部組织曽分担書記市委區委等偽职負責吸收及領導社會一般左傾青年份子及學生為党徒経施部生吸收已死之江荣顯陳俊業在逃之劉嘉武呂國昭及被告莊朝鐘許溪河由江荣顯介紹已死之黃碧泉及被告張建三嚴勝河尤昭荣再由黃碧泉介紹被告李金木暨陳俊業吸引被告賴水池及不識名之王劉張三人以及劉嘉武吸引被告黃士性傅鍾韓再由黃士性吸收劉嘉武之弟即被告劉嘉憲並経莊朝鐘吸收在逃之賴朝成及李舜兩之弟李舜治而呂煥章亦吸收被告林如松及已死之吳江海在逃之黃介石林金塗簡慶雲李継仁並由林如松轉介在逃之江森荣尤來榮黃伯和江順濱曹乙集又被告彭沐興劉水生係另由在逃市委陳福添吸引之江泰勇轉介之吳明正所吸收而彭沐興亦勸誘在逃之翁啓林吳樹培等人以及在逃各人犯所吸引之党徒甚多相継参加組织旋因部份党徒因身分暴露在市區不能立足乃由匪台工委會中部負責人劉志敬計劃建立三個地下武装大隊以該施部生呂煥章及在逃之李漢堂分任隊長即由呂煥章率張建三等数人於三十八年八月間先進入鴨潭山上覓定基地藉墾植作掩護因人數漸増経費無着其上級復指示以経濟鬥争維持生活並以暗殺為手段打擊特務工作當経施部生發動命令陳俊業江荣顯黃碧泉呂國昭莊朝鐘於同年十一月十八日晚九時許各攜帶刀槍窜入台中市倉庫利用合作社企圖搶刼向該社职員洪秋水等廹取金庫鑰匙未獲隨将該洪秋水綑纏後逸去同月三十日下午二時復経呂煥章發動由張建三與在逃之廖文珍化装旅客搭附台中通日月潭公路車該呂煥章親自等候於霧峰草湖站及二車後各出槍向旅客刦取新台幣二千六百七十元及手錶鋼筆眼鏡戒指金練等物並廹令司機將車開至小路上遁逸恐被追捕即轉入白毛山及石岡另闢基地又李漢堂亦夥党扵白毛山建立武裝基地並扵本年一月廾七日下午五時四十分發動其党徒在霧峰街某皮鞋店殺害台中縣大屯警察分局刑事組隊員黃金坤斃命同月二十六日晚十時許該陳俊業以其同事台中商業职業學校教導主任汪朝新係特務人員里常活動先與施部生謀議同意乃帶同江荣顯呂國昭前往寔施暗殺因夜間誤認同校教員畢克鈞為汪朝新將其擊斃二月七日中午十二時許該陳俊業復探知該校出納組長林荣華向台灣銀行領取経費亦與施部生率帶江泰勇張建三李金木預伏台中北區區公所附近路旁將林荣華所攜公款一萬四仟八百餘元全數刦去該施部生陳俊業等因犯案累累亦糾合其他党徒陸續上山開闢建立竹子坑大條及鴨潭两基地與呂煥章李漢堂互相聫絡呼應從事武裝叛乱経國防部保密局偵悉破案除陳俊業江荣顯黃碧泉吳江海當場图逃中弹斃命外計在白毛山竹子坑等處捕獲該施部生等十餘人及槍弹等物並緝獲闗係犯隋宗清温傳旺黃士楼一併移轉到部審辦\n　　　理　由\n被告施部生呂煥章張建三李金木莊朝鐘先後加入奸匪組织分別吸收党徒奉令組织地下武裝部隊嘯聚山林建立基地從事叛乱行為寔行経濟鬥争及打擊特務工作連續夥同槍刼台中市倉庫利用合作社財物未遂及截刦台中通日月潭公路車搭客財物台中商業职業學校出納組長林荣華所攜之公款並暗殺該校教員畢克鈞等事寔業據該被告等在保密局及本部審訊時一致供認不諱並経分電台中市及台中縣警察局省公路局台中段等處查覆属寔且有破案時當塲繳獲之大批槍弹可證是該被告等發展同志擴大地下武装組织建立基地寔施搶刦暗殺應觸犯共同以暴動意圖顛覆政府而着手寔行罪證明確至寔施槍殺等多次係暴動之手段為達成叛乱之目的當然吸收於暴動意图顛覆政府罪內其所犯情節重大罪無可逭均應依法處以極刑以昭烱戒被告林如松彭沐興黃士性劉嘉憲除加入匪党外該林如松彭沐興黃士性並分別吸收同志發展組织及該黃士性介紹購買土地作為建立武装寨穴劉嘉憲則往來於武裝基地聫絡溝通消息並受張建三黃士性輾轉教唆以其現充新社村國民兵隊附职務在新社鄉公所辦公之機會而盗取該外預印之空白國民身份證換發証明書十張偹為嘯聚山上之匪党掩護身份之用等事寔已據該被告等自認及互證不諱雖該被告等未参與施部生等所發動刦殺處行之意思聫絡及寔施然核其吸引同志發展組织嘯聚武装基地或負購辦供使用之物資及聫絡消息等工作不遺餘力亦應以意图顛覆政府而着手寔行之罪論科各處死刑以儆效尤至購辦供使用物資及教唆或盗取預印之身份證換發證書其目的為掩護身份以便利叛乱之活動與意图顛覆政府之罪係有牽連闗係應從一重處断被告嚴勝河許溪河尤昭荣劉水生傅鍾韓賴水池均参加奸党組织及該嚴勝河許溪河尤昭榮劉水生進入武装基地固據自認及互證無訛然彼等或係受人勸誘加入因身分暴露上山掩護或上山後係負種植燒飯等工作均無吸收他人入党及参與其他暴行尚難以意图顛覆政府論科僅能使負参加叛乱之組织罪除該嚴勝河時常对黃士楼加以教育灌輸左傾思想情莭較重自應以最高刑論科外餘均酌情處以適當之刑被告隋宗清雖否認有参加奸匪組织情事但據自承對社會現寔不滿言論時發牢騷致两度為匪嫌被逮更覺環境不佳乃受同事陳俊業以開墾種植為名引帶上山居住竹子坑武装基地帮助搭蓋草寮工作曽参加施部生等集會討論闗於上山原因觧决生活情形以及如何掩護身分接近民衆等諸問題不諱並経施部生等證訊無异是其思想左傾同情奸匪参加叛乱之集會亦應依法論科被告温傳旺固否認参加奸匪暴乱組织並辯稱亦不知獲案之施部生等係属奸匪份子云云但該匪等嘯聚於該被告製作竹工之草寮下坡距離僅一千步左右平時持用武器出入且已死之黃碧泉又與該被告素識並帶同两匪夥向其商借草寮共住已為該被告所不爭之事寔况據自稱看他們（指匪党）都是青年學生不像來墾荒的心裡很奇怪等語是該被告既知有異何不舉發雖據施部生等證述該被告確無参與組织闗係然其明知為匪諜而不檢举難辞其咎亦属觸犯刑章被告黃士楼雖経施部生等証述並未参加匪党惟其受乃兄黃士性嘱咐湏隔两天赴武装基地草寮一次為防外人闖入如發現附近有外人要趕快通知消息並素與嚴勝河接近受其教育灌輸各情在保密局及本部訊問時先後供詞一致亦應令負明知為匪諜而不檢舉罪刑繳案之白毛山竹子坑两處鹵獲之槍弹係属違禁及預偹或供犯罪所用之物均予沒收至該施部生呂煥章張建三李金木莊朝鐘林如松彭沐興黃士性劉嘉憲之全部財産除酌留其家属必需生活費外亦均應依法沒收\n基上論結合依修正惩治叛乱條例第二條苐一項第四條第一項第四款第五條第八條第一項苐十條第十二條惩治貪汚條例第三條第二款刑法第一百零一條第一項前段第一百條第一項第二十八條第二十九條第三十七條第一項第二項第三十八條第一項第一二两款第五十五條戡乱時期檢肅匪諜條例第九條刑事訴訟法第二百九十一條前段判决如主文\n中　華　民　國　三　十　九　年　九　月　七　日\n台灣省保安司令部軍法處\n審判官　殷敬文\n右正本證明與原本無异\n書記官　黃柱中\n中　華　民　國　三　十　九　年　九　月　日"
}