{
    "id": "15392",
    "name": "林明木",
    "gender": "男",
    "birth_h": "1927",
    "province": "臺灣省",
    "city": "臺北縣",
    "edu": "暫無資料",
    "d1_num": "暫無資料",
    "occupation": "台灣省郵政管理局會計股助理會計員",
    "age": "24",
    "d1_per1": "暫無資料",
    "d1_crime1": "暫無資料",
    "d1_crime1cat": "暫無資料",
    "d1_law1": "暫無資料",
    "d1_prosec": "無",
    "d1_pa1": "暫無資料",
    "d1_clk1": "暫無資料",
    "d2_doc": "公文（代電、稿、簽呈等）",
    "d2_num1": "(39)安澄字第2377號",
    "d2_authority": "台灣省保安司令部",
    "d2_main1": "參加叛亂組織",
    "d2_per1": "張添丁",
    "d2_per2": "李生財",
    "d2_per3": "許欽宗",
    "d2_per4": "林德旺",
    "d2_per5": "朱永祥",
    "d2_per6": "楊進豐",
    "d2_per7": "洪金木",
    "d2_per8": "蘇九",
    "d2_per9": "吳海瑞",
    "d2_per10": "郭兆慶",
    "d2_per11": "陳鏗",
    "d2_per12": "楊清順",
    "d2_per13": "賴子煥",
    "d2_per14": "蔡漢清",
    "d2_per15": "林向榮",
    "d2_per16": "陳健通",
    "d2_per17": "蕭成金",
    "d2_per18": "陳景通",
    "d2_per19": "林鏡明",
    "d2_per20": "林琳養",
    "d2_per21": "鄭添枝",
    "d2_per22": "凃龍西",
    "d2_per23": "王康旼",
    "d2_per24": "林傑鋼",
    "d2_term": "有",
    "d2_termy": "15",
    "d2_termm": "0",
    "d2_dpriv": "有",
    "d2_dprivy": "10",
    "d2_dprivm": "0",
    "d2_law1": "懲治叛亂條例",
    "d2_law1a": "5",
    "d2_j1": "端木棪",
    "d2_jpos1": "審判官",
    "d2_clk1": "韓醴泉",
    "d2_y": "39",
    "d2_m": "9",
    "d2_d": "7",
    "d3_doc": "公文（代電、稿、簽呈等）",
    "d3_num1": "法簽字第367號",
    "d3_authority": "國防部",
    "d3_crime1": "張添丁李生財許欽宗林德旺朱永祥於三十六七八年先後加入共匪組織吸收匪徒成立匪黨支部分別自任支部書記及連絡員等職發展工作被告楊進豐洪金木蘇九吳海瑞郭兆慶陳鏗楊清順賴子煥蔡漢清林向榮陳景通林鏡明林琳養鄭添枝凃龍西王康旼林明木林傑鋼先後參加匪黨事証均極明確",
    "d3_crime1cat": "參加叛亂之組織或集會者",
    "d3_j1": "郭寄嶠",
    "d3_jpos1": "副參謀總長(執行官)",
    "d3_y": "39",
    "d3_m": "10",
    "d3_d": "2",
    "d3_revrec": "同意",
    "d4_doc": "公文（代電、稿、簽呈等）",
    "d4_num1": "法簽字第367號",
    "d4_num2": "機秘(乙)第7422號",
    "d4_authority": "總統（府）",
    "d4_crime1": "未提及罪行",
    "d4_crime1cat": "未提及罪行",
    "d4_j1": "劉士毅",
    "d4_jpos1": "總統府參軍長",
    "d4_y": "39",
    "d4_m": "10",
    "d4_d": "4",
    "d4_revrec": "同意",
    "d5_doc": "公文（代電、稿、簽呈等）",
    "d5_num1": "法簽字第367號",
    "d5_num2": "機秘(乙)第7422號",
    "d5_authority": "總統（府）",
    "d5_crime1": "未提及罪行",
    "d5_crime1cat": "未提及罪行",
    "d5_j1": "蔣中正",
    "d5_jpos1": "總統",
    "d5_y": "39",
    "d5_m": "10",
    "d5_d": "6",
    "d5_presw": "如擬",
    "d5_revrec": "同意",
    "d6_doc": "公文（代電、稿、簽呈等）",
    "d6_num1": "聯(芬)字第390264號",
    "d6_authority": "總統（府）",
    "d6_crime1": "未提及罪行",
    "d6_crime1cat": "未提及罪行",
    "d6_j1": "蔡大冶",
    "d6_jpos1": "總統府駐國防部連絡室高參",
    "d6_y": "39",
    "d6_m": "10",
    "d6_d": "7",
    "d6_revrec": "同意",
    "d7_doc": "公文（代電、稿、簽呈等）",
    "d7_num1": "(39)勁助字第894號",
    "d7_authority": "國防部",
    "d7_crime1": "未提及罪行",
    "d7_crime1cat": "未提及罪行",
    "d7_j1": "鄭介民",
    "d7_jpos1": "參謀次長",
    "d7_y": "39",
    "d7_m": "10",
    "d7_d": "19",
    "d7_revrec": "同意",
    "d8_doc": "判決書",
    "d8_num1": "(39)安澄字第2377號",
    "d8_authority": "台灣省保安司令部",
    "d8_main1": "參加叛亂組織",
    "d8_per1": "張添丁",
    "d8_per2": "李生財",
    "d8_per3": "許欽宗",
    "d8_per4": "林德旺",
    "d8_per5": "朱永祥",
    "d8_per6": "楊進豐",
    "d8_per7": "洪金木",
    "d8_per8": "蘇九",
    "d8_per9": "吳海瑞",
    "d8_per10": "郭兆慶",
    "d8_per11": "陳鏗",
    "d8_per12": "楊清順",
    "d8_per13": "賴子煥",
    "d8_per14": "蔡漢清",
    "d8_per15": "林向榮",
    "d8_per16": "陳健通",
    "d8_per17": "蕭成金",
    "d8_per18": "陳景通",
    "d8_per19": "林鏡明",
    "d8_per20": "林琳養",
    "d8_per21": "鄭添枝",
    "d8_per22": "凃龍西",
    "d8_per23": "王康旼",
    "d8_per24": "林傑鋼",
    "d8_term": "有",
    "d8_termy": "15",
    "d8_termm": "0",
    "d8_dpriv": "有",
    "d8_dprivy": "10",
    "d8_dprivm": "0",
    "d8_law1": "懲治叛亂條例",
    "d8_law1a": "5",
    "d8_j1": "端木棪",
    "d8_jpos1": "審判官",
    "d8_clk1": "韓醴泉",
    "d8_y": "39",
    "d8_m": "10",
    "d8_d": "19",
    "d8_rejud": "無",
    "d8_revrec": "不適用",
    "f_authority": "台灣省保安司令部",
    "f_jyear": "39",
    "f_num": "(39)安澄字第2377號",
    "f_main1": "參加叛亂組織",
    "f_group": "歷年辦理匪案彙編：匪台灣省工委會鐵路部份組織",
    "f_per1": "張添丁",
    "f_per2": "李生財",
    "f_per3": "許欽宗",
    "f_per4": "林德旺",
    "f_per5": "朱永祥",
    "f_per6": "楊進豐",
    "f_per7": "洪金木",
    "f_per8": "蘇九",
    "f_per9": "吳海瑞",
    "f_per10": "郭兆慶",
    "f_per11": "陳鏗",
    "f_per12": "楊清順",
    "f_per13": "賴子煥",
    "f_per14": "蔡漢清",
    "f_per15": "林向榮",
    "f_per16": "陳健通",
    "f_per17": "蕭成金",
    "f_per18": "陳景通",
    "f_per19": "林鏡明",
    "f_per20": "林琳養",
    "f_per21": "鄭添枝",
    "f_per22": "凃龍西",
    "f_per23": "王康旼",
    "f_per24": "林傑鋼",
    "f_law1": "懲治叛亂條例",
    "f_law1a": "5",
    "f_penaltytxt": "有期徒刑15年",
    "f_term": "有",
    "f_termy": "15",
    "f_termm": "0",
    "f_forf": "無",
    "f_j1": "端木棪",
    "f_clk1": "韓醴泉",
    "f_y": "39",
    "f_m": "10",
    "f_d": "19",
    "f_txt": "暫無資料"
}