{
    "id": "17336",
    "name": "黃志強2",
    "gender": "男",
    "birth_h": "1946",
    "province": "上海市",
    "edu": "暫無資料",
    "d1_num": "暫無資料",
    "occupation": "海員",
    "age": "24",
    "d1_per1": "暫無資料",
    "d1_crime1": "暫無資料",
    "d1_crime1cat": "暫無資料",
    "d1_law1": "暫無資料",
    "d1_prosec": "無",
    "d1_pa1": "暫無資料",
    "d1_clk1": "暫無資料",
    "d2_doc": "其他",
    "d2_num1": "(59)裁字第51號",
    "d2_num2": "(59)勁需字第141號",
    "d2_authority": "台灣警備總司令部",
    "d2_main1": "交付感化三年",
    "d2_edu": "有",
    "d2_eduy": "3",
    "d2_edum": "0",
    "d2_crime1": "黃志強平時言詞左傾，經常閱讀毛匪語錄……五十八年九月隨東方嘉華號輪從英來台途中，在該輪水手部黑板上書寫毛匪語錄及毛匪思想萬歲等文字",
    "d2_crime1cat": "情節輕微而有感化必要者，交付感化",
    "d2_law1": "檢肅匪諜條例",
    "d2_law1a": "8",
    "d2_law1s": "1",
    "d2_law1i": "2",
    "d2_law2": "戡亂時期匪諜交付感化辦法",
    "d2_law2a": "2",
    "d2_law2s": "1",
    "d2_law3": "戡亂時期匪諜交付感化辦法",
    "d2_law3a": "2",
    "d2_law3s": "2",
    "d2_j1": "孟廷杰",
    "d2_jpos1": "審判官",
    "d2_clk1": "楊永祥",
    "d2_y": "59",
    "d2_m": "1",
    "d2_d": "13",
    "d2_rejud": "無",
    "f_authority": "台灣警備總司令部",
    "f_jyear": "59",
    "f_num": "(59)裁字第51號；(59)勁需字第141號",
    "f_main1": "交付感化三年",
    "f_law1": "檢肅匪諜條例",
    "f_law1a": "8",
    "f_law1s": "1",
    "f_law1i": "2",
    "f_law2": "戡亂時期匪諜交付感化辦法",
    "f_law2a": "2",
    "f_law2s": "1",
    "f_law3": "戡亂時期匪諜交付感化辦法",
    "f_law3a": "2",
    "f_law3s": "2",
    "f_penaltytxt": "交付感化",
    "f_edu": "有",
    "f_eduy": "3",
    "f_edum": "0",
    "f_forf": "x",
    "f_j1": "孟廷杰",
    "f_clk1": "楊永祥",
    "f_y": "59",
    "f_m": "1",
    "f_d": "13",
    "f_txt": "暫無資料"
}