{
    "id": "23824",
    "name": "陳利餘",
    "gender": "男",
    "province": "福建",
    "city": "林森縣",
    "edu": "暫無資料",
    "d1_num": "暫無資料",
    "occupation": "福建游擊總部閩北地區司令部第六支隊列兵",
    "age": "25",
    "d1_per1": "暫無資料",
    "d1_crime1": "暫無資料",
    "d1_crime1cat": "暫無資料",
    "d1_law1": "暫無資料",
    "d1_prosec": "無",
    "d1_pa1": "暫無資料",
    "d1_clk1": "暫無資料",
    "d2_doc": "公文（代電、稿、簽呈等）",
    "d2_num1": "(42)清評字第46號",
    "d2_authority": "陸軍總司令部",
    "d2_pa1": "唐億年",
    "d2_atty1": "王志謙",
    "d2_attycat": "公設",
    "d2_main1": "共同為叛徒刺探關於軍事上之秘密",
    "d2_per1": "陳敬",
    "d2_per2": "林漢雄",
    "d2_per3": "謝永平",
    "d2_per4": "林錡",
    "d2_per5": "黃雲奕",
    "d2_per6": "程峰",
    "d2_per7": "林我鶴",
    "d2_per8": "張文彬",
    "d2_life": "有",
    "d2_dpriv": "有",
    "d2_dprivy": "終身",
    "d2_law1": "懲治叛亂條例",
    "d2_law1a": "4",
    "d2_law1s": "1",
    "d2_law1i": "5",
    "d2_law2": "刑法",
    "d2_law2a": "28",
    "d2_j1": "劉建章",
    "d2_j2": "王有樑",
    "d2_j3": "傅春生",
    "d2_jpos1": "審判長",
    "d2_jpos2": "審判官",
    "d2_jpos3": "審判官",
    "d2_clk1": "劉冠亞",
    "d2_y": "42",
    "d2_m": "4",
    "d2_d": "18",
    "d3_doc": "公文（代電、稿、簽呈等）",
    "d3_num1": "(42)廉龐字第1458號",
    "d3_authority": "國防部",
    "d3_crime1": "被告陳敬……三十八年閩境陷匪集結義民游擊次年秋率同隊員即被告謝永平陳利餘及邱武等返福州投匪交出隊員一百一十七人槍械二百餘枝匪方知其與我駐白犬島海堡部隊人員有舊……匪幫心有未甘乃命其親率謝永平陳利餘往白犬刺探軍情至則以匪嫌被扣以無確證於四十年三月釋放乃使陳利餘留充海堡第六支隊列兵",
    "d3_crime1cat": "為叛徒作嚮導或刺探蒐集傳遞關於軍事上或政治上之秘密者",
    "d3_j1": "周至柔",
    "d3_jpos1": "參謀總長",
    "d3_y": "42",
    "d3_m": "6",
    "d3_d": "20",
    "d3_revrec": "同意",
    "d4_doc": "公文（代電、稿、簽呈等）",
    "d4_num1": "(42)機秘(乙)字第72-37號",
    "d4_authority": "總統（府）",
    "d4_crime1": "被告等九名……於三十八年由陳敬率隊投匪後因匪方偵悉陳等與我駐白犬島海堡部隊有舊……復派陳敬親率陳利餘謝永平二人進入白犬島馬祖島除陳利餘留充海堡部隊列兵外",
    "d4_crime1cat": "為叛徒作嚮導或刺探蒐集傳遞關於軍事上或政治上之秘密者",
    "d4_j1": "桂永清",
    "d4_jpos1": "總統府參軍長",
    "d4_y": "42",
    "d4_m": "7",
    "d4_d": "9",
    "d4_revrec": "同意",
    "d5_doc": "公文（代電、稿、簽呈等）",
    "d5_num1": "(42)機秘(乙)字第72-37號",
    "d5_authority": "總統（府）",
    "d5_crime1": "未提及罪行",
    "d5_crime1cat": "未提及罪行",
    "d5_j1": "蔣中正",
    "d5_jpos1": "總統",
    "d5_y": "42",
    "d5_m": "8",
    "d5_d": "13",
    "d5_presw": "如擬",
    "d5_revrec": "同意",
    "d6_doc": "公文（代電、稿、簽呈等）",
    "d6_num1": "(42)強仁字第3408號",
    "d6_authority": "總統（府）",
    "d6_crime1": "未提及罪行",
    "d6_crime1cat": "未提及罪行",
    "d6_j1": "桂永清",
    "d6_jpos1": "總統府參軍長",
    "d6_y": "42",
    "d6_m": "8",
    "d6_d": "15",
    "d6_revrec": "同意",
    "d7_doc": "判決書",
    "d7_num1": "(42)清評字第46號",
    "d7_authority": "陸軍總司令部",
    "d7_pa1": "唐億年",
    "d7_atty1": "王志謙",
    "d7_attycat": "公設",
    "d7_main1": "共同為叛徒刺探關於軍事上之秘密",
    "d7_per1": "陳敬",
    "d7_per2": "林漢雄",
    "d7_per3": "謝永平",
    "d7_per4": "林錡",
    "d7_per5": "黃雲奕",
    "d7_per6": "程峰",
    "d7_per7": "林我鶴",
    "d7_per8": "張文彬",
    "d7_life": "有",
    "d7_dpriv": "有",
    "d7_dprivy": "終身",
    "d7_law1": "懲治叛亂條例",
    "d7_law1a": "4",
    "d7_law1s": "1",
    "d7_law1i": "5",
    "d7_law2": "刑法",
    "d7_law2a": "28",
    "d7_j1": "劉建章",
    "d7_j2": "王有樑",
    "d7_j3": "傅春生",
    "d7_jpos1": "審判長",
    "d7_jpos2": "審判官",
    "d7_jpos3": "審判官",
    "d7_clk1": "劉冠亞",
    "d7_y": "42",
    "d7_m": "8",
    "d7_d": "15",
    "d7_rejud": "無",
    "d7_revrec": "不適用",
    "f_authority": "陸軍總司令部",
    "f_jyear": "42",
    "f_num": "(42)清評字第46號",
    "f_pa1": "唐億年",
    "f_atty1": "王志謙",
    "f_attycat": "公設",
    "f_main1": "共同為叛徒刺探關於軍事上之秘密",
    "f_per1": "陳敬",
    "f_per2": "林漢雄",
    "f_per3": "謝永平",
    "f_per4": "林錡",
    "f_per5": "黃雲奕",
    "f_per6": "程峰",
    "f_per7": "林我鶴",
    "f_per8": "張文彬",
    "f_law1": "懲治叛亂條例",
    "f_law1a": "4",
    "f_law1s": "1",
    "f_law1i": "5",
    "f_law2": "刑法",
    "f_law2a": "28",
    "f_penaltytxt": "暫無資料",
    "f_life": "有",
    "f_forf": "有",
    "f_j1": "劉建章",
    "f_j2": "王有樑",
    "f_j3": "傅春生",
    "f_clk1": "劉冠亞",
    "f_y": "42",
    "f_m": "8",
    "f_d": "15",
    "f_txt": "暫無資料"
}