{
    "id": "24238",
    "name": "房心田 二",
    "gender": "男",
    "birth_h": "1916",
    "province": "山東",
    "city": "萊陽縣",
    "edu": "暫無資料",
    "d1_num": "暫無資料",
    "age": "48",
    "d1_per1": "暫無資料",
    "d1_crime1cat": "暫無資料",
    "d1_law1": "暫無資料",
    "d1_prosec": "無",
    "d1_pa1": "暫無資料",
    "d1_clk1": "暫無資料",
    "d2_doc": "判決書",
    "d2_num1": "(56)訴字第2號",
    "d2_authority": "臺灣高等法院",
    "d2_pa1": "沈嶽#",
    "d2_main1": "本件免訴",
    "d2_j1": "施##",
    "d2_j2": "林宗肯",
    "d2_j3": "張##",
    "d2_jpos1": "審判長推事",
    "d2_jpos2": "推事",
    "d2_jpos3": "推事",
    "d2_y": "53",
    "d2_m": "5",
    "d2_d": "7",
    "d2_rejud": "無",
    "f_authority": "台灣高等法院",
    "f_jyear": "53",
    "f_num": "(52)訴字第2號",
    "f_pa1": "沈##",
    "f_main1": "本件免訴",
    "f_penaltytxt": "公訴不受理；內亂罪免訴",
    "f_forf": "x",
    "f_j1": "蔡慕陶",
    "f_j2": "趙華通",
    "f_j3": "唐湘濤",
    "f_clk1": "李子新",
    "f_y": "53",
    "f_m": "5",
    "f_d": "7"
}