{
    "id": "24445",
    "name": "林家榮1 一",
    "gender": "男",
    "birth_h": "1928",
    "province": "臺灣省",
    "city": "臺北縣",
    "edu": "日本工業學校",
    "d1_num": "暫無資料",
    "occupation": "商",
    "age": "27",
    "d1_per1": "暫無資料",
    "d1_crime1": "暫無資料",
    "d1_crime1cat": "暫無資料",
    "d1_law1": "暫無資料",
    "d1_prosec": "無",
    "d1_pa1": "暫無資料",
    "d1_clk1": "暫無資料",
    "d2_doc": "判決書",
    "d2_num1": "(43)審三字第110號",
    "d2_authority": "台灣省保安司令部",
    "d2_pa1": "蕭與規",
    "d2_atty1": "羅鎮",
    "d2_attycat": "公設",
    "d2_main1": "故意陷害誣告他人參加叛亂之組織",
    "d2_term": "有",
    "d2_termy": "12",
    "d2_termm": "0",
    "d2_dpriv": "有",
    "d2_dprivy": "10",
    "d2_dprivm": "0",
    "d2_law1": "檢肅匪諜條例",
    "d2_law1a": "10",
    "d2_law1s": "1",
    "d2_law2": "懲治叛亂條例",
    "d2_law2a": "5",
    "d2_j1": "周咸慶",
    "d2_j2": "彭國壎",
    "d2_j3": "邢炎初",
    "d2_jpos1": "審判長",
    "d2_jpos2": "審判官",
    "d2_jpos3": "審判官",
    "d2_clk1": "管萃恩",
    "d2_y": "43",
    "d2_m": "10",
    "d2_d": "14",
    "d2_rejud": "無",
    "f_authority": "台灣省保安司令部",
    "f_jyear": "43",
    "f_num": "(43)審三字第110號",
    "f_pa1": "蕭與規",
    "f_atty1": "羅鎮",
    "f_attycat": "公設",
    "f_main1": "故意陷害誣告他人參加叛亂之組織",
    "f_law1": "檢肅匪諜條例",
    "f_law1a": "10",
    "f_law1s": "1",
    "f_law2": "懲治叛亂條例",
    "f_law2a": "5",
    "f_penaltytxt": "有期徒刑12年褫奪公權10年",
    "f_term": "有",
    "f_termy": "12",
    "f_termm": "0",
    "f_forf": "無",
    "f_j1": "周咸慶",
    "f_j2": "彭國壎",
    "f_j3": "邢炎初",
    "f_clk1": "管萃恩",
    "f_y": "43",
    "f_m": "11",
    "f_d": "24",
    "f_txt": "暫無資料"
}