{
    "id": "24684",
    "name": "盛廷生",
    "gender": "男",
    "province": "江蘇",
    "city": "銅山縣",
    "edu": "暫無資料",
    "d1_num": "暫無資料",
    "occupation": "陸軍第八二九七部隊上士炮長",
    "age": "26",
    "d1_per1": "暫無資料",
    "d1_crime1": "暫無資料",
    "d1_crime1cat": "暫無資料",
    "d1_law1": "暫無資料",
    "d1_prosec": "無",
    "d1_pa1": "暫無資料",
    "d1_clk1": "暫無資料",
    "d2_doc": "其他",
    "d2_num1": "(43)清淨字第62號",
    "d2_authority": "國防部",
    "d2_main1": "交付感化期間另以命令定之",
    "d2_edu": "有",
    "d2_eduy": "3",
    "d2_edum": "0",
    "d2_crime1": "惟其年輕狂妄染成犯罪習慣且曾受宮匪樹桐之影响態度模稄跡近可疑應予感化必要",
    "d2_crime1cat": "情節輕微而有感化必要者，交付感化",
    "d2_law1": "檢肅匪諜條例",
    "d2_law1a": "8",
    "d2_law1s": "1",
    "d2_law1i": "2",
    "d2_j1": "汪喬椿",
    "d2_jpos1": "審判官",
    "d2_clk1": "鄭惠民",
    "d2_y": "43",
    "d2_m": "2",
    "d2_d": "18",
    "d2_rejud": "無",
    "f_authority": "國防部",
    "f_jyear": "43",
    "f_num": "(43)清淨字第62號",
    "f_main1": "交付感化期間另以命令定之",
    "f_law1": "檢肅匪諜條例",
    "f_law1a": "8",
    "f_law1s": "1",
    "f_law1i": "2",
    "f_penaltytxt": "暫無資料",
    "f_edu": "有",
    "f_eduy": "3",
    "f_edum": "0",
    "f_forf": "x",
    "f_j1": "汪喬椿",
    "f_clk1": "鄭惠民",
    "f_y": "43",
    "f_m": "2",
    "f_d": "18",
    "f_txt": "暫無資料"
}