{
    "id": "24691",
    "name": "吳文彬",
    "gender": "男",
    "province": "暫無資料",
    "city": "暫無資料",
    "edu": "暫無資料",
    "d1_num": "暫無資料",
    "occupation": "商",
    "age": "39",
    "d1_per1": "暫無資料",
    "d1_crime1": "暫無資料",
    "d1_crime1cat": "暫無資料",
    "d1_law1": "暫無資料",
    "d1_prosec": "無",
    "d1_pa1": "暫無資料",
    "d1_clk1": "暫無資料",
    "d2_doc": "判決書",
    "d2_num1": "(46)判字第1545號",
    "d2_authority": "台灣高等法院",
    "d2_pa1": "莊彭年",
    "d2_atty1": "葉葦",
    "d2_attycat": "選任",
    "d2_main1": "通謀敵國充任有關軍事之職役",
    "d2_per1": "邱于華",
    "d2_term": "有",
    "d2_termy": "4",
    "d2_termm": "0",
    "d2_dpriv": "有",
    "d2_dprivy": "4",
    "d2_dprivm": "0",
    "d2_law1": "刑法",
    "d2_law1a": "59",
    "d2_law2": "懲治漢奸條例",
    "d2_law2a": "2",
    "d2_law2s": "1",
    "d2_law2i": "8",
    "d2_law3": "懲治漢奸條例",
    "d2_law3a": "2",
    "d2_law3s": "2",
    "d2_j1": "夏華夏",
    "d2_j2": "陳思永",
    "d2_j3": "陳鐘",
    "d2_jpos1": "審判長推事",
    "d2_jpos2": "推事",
    "d2_jpos3": "推事",
    "d2_y": "46",
    "d2_m": "5",
    "d2_d": "13",
    "d2_rejud": "無",
    "f_authority": "台灣高等法院",
    "f_jyear": "46",
    "f_num": "(46)判字第1545號",
    "f_pa1": "莊彭年",
    "f_atty1": "葉葦",
    "f_attycat": "選任",
    "f_main1": "通謀敵國充任有關軍事之職役",
    "f_per1": "邱于華",
    "f_law1": "刑法",
    "f_law1a": "59",
    "f_law2": "懲治漢奸條例",
    "f_law2a": "2",
    "f_law2s": "1",
    "f_law2i": "8",
    "f_law3": "懲治漢奸條例",
    "f_law3a": "2",
    "f_law3s": "2",
    "f_penaltytxt": "暫無資料",
    "f_term": "有",
    "f_termy": "4",
    "f_termm": "0",
    "f_forf": "有",
    "f_j1": "夏華夏",
    "f_j2": "陳思永",
    "f_j3": "陳鐘",
    "f_y": "46",
    "f_m": "5",
    "f_d": "13",
    "f_txt": "暫無資料"
}