{
    "id": "26944",
    "name": "馬國輝",
    "gender": "男",
    "birth_h": "1963",
    "province": "山東",
    "city": "平度縣",
    "edu": "西商工商二年級肄業",
    "d1_authority": "台灣警備總司令部",
    "d1_num": "(74)警檢處字第017號",
    "occupation": "無",
    "age": "22",
    "d1_prosec": "無",
    "d1_pa1": "王政琬",
    "d1_clk1": "莊文仁",
    "d1_y": "74",
    "d1_m": "1",
    "d1_d": "16",
    "f_authority": "台灣警備總司令部",
    "f_jyear": "74",
    "f_num": "(74)警檢處字第017號",
    "f_penaltytxt": "不起訴處分",
    "f_forf": "x",
    "f_j1": "王政琬",
    "f_clk1": "莊文仁",
    "f_y": "74",
    "f_m": "1",
    "f_d": "23",
    "f_txt": "暫無資料"
}