{
    "id": "27180",
    "name": "林阿順",
    "gender": "男",
    "province": "臺灣省",
    "city": "桃園縣",
    "edu": "暫無資料",
    "d1_authority": "台灣省保安司令部",
    "d1_num": "(47)守宇字第946號",
    "occupation": "農",
    "age": "48",
    "d1_per1": "邱爐",
    "d1_per2": "邱榮源",
    "d1_prosec": "無",
    "d1_pa1": "劉守垿",
    "d1_clk1": "陳道源",
    "d1_y": "47",
    "d1_m": "6",
    "d1_d": "3",
    "f_authority": "台灣省保安司令部",
    "f_jyear": "47",
    "f_num": "(47)守宇字第946號",
    "f_per1": "邱爐",
    "f_per2": "邱榮源",
    "f_penaltytxt": "不起訴處分",
    "f_forf": "x",
    "f_j1": "劉守垿",
    "f_clk1": "陳道源",
    "f_y": "47",
    "f_m": "6",
    "f_d": "3",
    "f_txt": "暫無資料"
}